常见于 index 相关方法，测试代码

    public class RelationalOperatorTest {
        private int test() {
            return 0;
        }

        public void test1() {
            int i = test();
            if (i > -1) {
                i = 9;
            }
        }

        public void test2() {
            int i = test();
            if (i >= 0) {
                i = 9;
            }
        }
    }
    
    字节码
    
    // class version 52.0 (52)
    // access flags 0x21
    public class com/pingfangx/study/tutorial/learning_the_java_language/language_basics/RelationalOperatorTest {

      // compiled from: RelationalOperatorTest.java

      // access flags 0x1
      public <init>()V
       L0
        LINENUMBER 9 L0
        ALOAD 0
        INVOKESPECIAL java/lang/Object.<init> ()V
        RETURN
       L1
        LOCALVARIABLE this Lcom/pingfangx/study/tutorial/learning_the_java_language/language_basics/RelationalOperatorTest; L0 L1 0
        MAXSTACK = 1
        MAXLOCALS = 1

      // access flags 0x2
      private test()I
       L0
        LINENUMBER 11 L0
        ICONST_0
        IRETURN
       L1
        LOCALVARIABLE this Lcom/pingfangx/study/tutorial/learning_the_java_language/language_basics/RelationalOperatorTest; L0 L1 0
        MAXSTACK = 1
        MAXLOCALS = 1

      // access flags 0x1
      public test1()V
       L0
        LINENUMBER 15 L0
        ALOAD 0
        INVOKESPECIAL com/pingfangx/study/tutorial/learning_the_java_language/language_basics/RelationalOperatorTest.test ()I
        ISTORE 1
       L1
        LINENUMBER 16 L1
        ILOAD 1
        ICONST_M1
        IF_ICMPLE L2
       L3
        LINENUMBER 17 L3
        BIPUSH 9
        ISTORE 1
       L2
        LINENUMBER 19 L2
       FRAME APPEND [I]
        RETURN
       L4
        LOCALVARIABLE this Lcom/pingfangx/study/tutorial/learning_the_java_language/language_basics/RelationalOperatorTest; L0 L4 0
        LOCALVARIABLE i I L1 L4 1
        MAXSTACK = 2
        MAXLOCALS = 2

      // access flags 0x1
      public test2()V
       L0
        LINENUMBER 22 L0
        ALOAD 0
        INVOKESPECIAL com/pingfangx/study/tutorial/learning_the_java_language/language_basics/RelationalOperatorTest.test ()I
        ISTORE 1
       L1
        LINENUMBER 23 L1
        ILOAD 1
        IFLT L2
       L3
        LINENUMBER 24 L3
        BIPUSH 9
        ISTORE 1
       L2
        LINENUMBER 26 L2
       FRAME APPEND [I]
        RETURN
       L4
        LOCALVARIABLE this Lcom/pingfangx/study/tutorial/learning_the_java_language/language_basics/RelationalOperatorTest; L0 L4 0
        LOCALVARIABLE i I L1 L4 1
        MAXSTACK = 1
        MAXLOCALS = 2
    }

    重点查看
    test1
        加载变量
        ILOAD 1
        压入常量 -1
        ICONST_M1
        如果 变量 <= -1 跳到 L2
        IF_ICMPLE L2
    
    test2
        加载变量
        ILOAD 1
        如果 变量 < 0 跳到 L2
        IFLT L2
        
# 结论
与 0 比较更优
# 因为字节码使用跳转，字节码在进行判断时，与我们代码中的判断相反
    如果 命题
        命题真代码块
    否则
        命题假代码块
        
    翻译为字节码就成了
    如果 否命题，则跳转到“否则”
        命题成功代码块
    否则
        命题失败代码块
        
    所以前面的示例中 if(i>-1) 处理为 如果 i<=-1 则跳转
    if(i>=0) 处理为 如果 <0 则跳围
    
# 与 0 比较有特殊的指令集
可以看到，与 -1 比较，要使用 IF_ICMPLE，它需要 2 个操作栈

而与 0 比较，则使用 IFLT，只需要 1 个操作栈

比较 <= 肯定不会先比较 < 再比较 =，具体怎么实现的暂时不知道

所以认为与 0 相关的比较更优