示例代码

    public class BridgeMethodTest {
        class SupperType<T> {
            public T update(T t) {
                return t;
            }
        }

        class SubType extends SupperType<Integer> {
            @Override
            public Integer update(Integer integer) {
                return super.update(integer);
            }
        }

        @Test
        public void test() {
            SupperType<Integer> supperType = new SubType();
            //方法签名是 Object
            supperType.update(1);
            SubType subType = new SubType();
            //方法签名是 Integer
            subType.update(2);
        }
    }
    
    字节码
    // class version 52.0 (52)
    // access flags 0x20
    // signature Lcom/pingfangx/study/tutorial/generics/BridgeMethodTest$SupperType<Ljava/lang/Integer;>;
    // declaration: com/pingfangx/study/tutorial/generics/BridgeMethodTest$SubType extends com.pingfangx.study.tutorial.generics.BridgeMethodTest$SupperType<java.lang.Integer>
    class com/pingfangx/study/tutorial/generics/BridgeMethodTest$SubType extends com/pingfangx/study/tutorial/generics/BridgeMethodTest$SupperType {

      // compiled from: BridgeMethodTest.java
      // access flags 0x0
      INNERCLASS com/pingfangx/study/tutorial/generics/BridgeMethodTest$SubType com/pingfangx/study/tutorial/generics/BridgeMethodTest SubType
      // access flags 0x0
      INNERCLASS com/pingfangx/study/tutorial/generics/BridgeMethodTest$SupperType com/pingfangx/study/tutorial/generics/BridgeMethodTest SupperType

      // access flags 0x1010
      final synthetic Lcom/pingfangx/study/tutorial/generics/BridgeMethodTest; this$0

      // access flags 0x0
      <init>(Lcom/pingfangx/study/tutorial/generics/BridgeMethodTest;)V
       L0
        LINENUMBER 18 L0
        ALOAD 0
        ALOAD 1
        PUTFIELD com/pingfangx/study/tutorial/generics/BridgeMethodTest$SubType.this$0 : Lcom/pingfangx/study/tutorial/generics/BridgeMethodTest;
        ALOAD 0
        ALOAD 1
        INVOKESPECIAL com/pingfangx/study/tutorial/generics/BridgeMethodTest$SupperType.<init> (Lcom/pingfangx/study/tutorial/generics/BridgeMethodTest;)V
        RETURN
       L1
        LOCALVARIABLE this Lcom/pingfangx/study/tutorial/generics/BridgeMethodTest$SubType; L0 L1 0
        LOCALVARIABLE this$0 Lcom/pingfangx/study/tutorial/generics/BridgeMethodTest; L0 L1 1
        MAXSTACK = 2
        MAXLOCALS = 2

      // access flags 0x1
      public update(Ljava/lang/Integer;)Ljava/lang/Integer;
       L0
        LINENUMBER 21 L0
        ALOAD 0
        ALOAD 1
        INVOKESPECIAL com/pingfangx/study/tutorial/generics/BridgeMethodTest$SupperType.update (Ljava/lang/Object;)Ljava/lang/Object;
        CHECKCAST java/lang/Integer
        ARETURN
       L1
        LOCALVARIABLE this Lcom/pingfangx/study/tutorial/generics/BridgeMethodTest$SubType; L0 L1 0
        LOCALVARIABLE integer Ljava/lang/Integer; L0 L1 1
        MAXSTACK = 2
        MAXLOCALS = 2

      // access flags 0x1041
      public synthetic bridge update(Ljava/lang/Object;)Ljava/lang/Object;
       L0
        LINENUMBER 18 L0
        ALOAD 0
        ALOAD 1
        CHECKCAST java/lang/Integer
        INVOKEVIRTUAL com/pingfangx/study/tutorial/generics/BridgeMethodTest$SubType.update (Ljava/lang/Integer;)Ljava/lang/Integer;
        ARETURN
       L1
        LOCALVARIABLE this Lcom/pingfangx/study/tutorial/generics/BridgeMethodTest$SubType; L0 L1 0
        MAXSTACK = 2
        MAXLOCALS = 2
    }


* 为什么会需要桥接方法  
类型擦除后，子类方法与父类方法签名不致，不能正确覆盖
* 桥接方法如何实现  
将父类擦除后的类型，进行强制转换，调用子类的方法