* 实例变量的初始化程序块看起来就像静态初始化程序块，但没有 static 关键字
* Java 编译器将初始化程序块复制到**每个**构造函数中。

测试代码

    public class InitializerBlockTest {
        private class TestClass {
            {
                field = 1;
            }

            private int field = 0;

            {
                field = 2;
            }

            public TestClass() {
            }

            public TestClass(int field) {
                this.field = field;
            }
        }

        @Test
        public void test() {
            //按顺序
            Assert.assertEquals(2, new TestClass().field);
            //插入到开头
            Assert.assertEquals(3, new TestClass(3).field);
        }
    }
    
    编译结果
    private class TestClass {
        private int field = 1;

        public TestClass() {
            this.field = 0;
            this.field = 2;
        }

        public TestClass(int field) {
            this.field = 0;
            this.field = 2;
            this.field = field;
        }
    }
    
    字节码
    // class version 52.0 (52)
    // access flags 0x20
    class com/pingfangx/study/tutorial/learning_the_java_language/classes_and_objects/init_fields/InitializerBlockTest$TestClass {

      // compiled from: InitializerBlockTest.java
      // access flags 0x2
      private INNERCLASS com/pingfangx/study/tutorial/learning_the_java_language/classes_and_objects/init_fields/InitializerBlockTest$TestClass com/pingfangx/study/tutorial/learning_the_java_language/classes_and_objects/init_fields/InitializerBlockTest TestClass

      // access flags 0x2
      private I field

      // access flags 0x1010
      final synthetic Lcom/pingfangx/study/tutorial/learning_the_java_language/classes_and_objects/init_fields/InitializerBlockTest; this$0

      // access flags 0x1
      public <init>(Lcom/pingfangx/study/tutorial/learning_the_java_language/classes_and_objects/init_fields/InitializerBlockTest;)V
       L0
        LINENUMBER 22 L0
        ALOAD 0
        ALOAD 1
        PUTFIELD com/pingfangx/study/tutorial/learning_the_java_language/classes_and_objects/init_fields/InitializerBlockTest$TestClass.this$0 : Lcom/pingfangx/study/tutorial/learning_the_java_language/classes_and_objects/init_fields/InitializerBlockTest;
        ALOAD 0
        INVOKESPECIAL java/lang/Object.<init> ()V
       L1
        LINENUMBER 13 L1
        ALOAD 0
        //赋值 1
        ICONST_1
        PUTFIELD com/pingfangx/study/tutorial/learning_the_java_language/classes_and_objects/init_fields/InitializerBlockTest$TestClass.field : I
       L2
        LINENUMBER 16 L2
        ALOAD 0
        //赋值 0
        ICONST_0
        PUTFIELD com/pingfangx/study/tutorial/learning_the_java_language/classes_and_objects/init_fields/InitializerBlockTest$TestClass.field : I
       L3
        LINENUMBER 19 L3
        ALOAD 0
        //赋值 2
        ICONST_2
        PUTFIELD com/pingfangx/study/tutorial/learning_the_java_language/classes_and_objects/init_fields/InitializerBlockTest$TestClass.field : I
       L4
        LINENUMBER 23 L4
        RETURN
       L5
        LOCALVARIABLE this Lcom/pingfangx/study/tutorial/learning_the_java_language/classes_and_objects/init_fields/InitializerBlockTest$TestClass; L0 L5 0
        MAXSTACK = 2
        MAXLOCALS = 2

      // access flags 0x1
      public <init>(Lcom/pingfangx/study/tutorial/learning_the_java_language/classes_and_objects/init_fields/InitializerBlockTest;I)V
       L0
        LINENUMBER 25 L0
        ALOAD 0
        ALOAD 1
        PUTFIELD com/pingfangx/study/tutorial/learning_the_java_language/classes_and_objects/init_fields/InitializerBlockTest$TestClass.this$0 : Lcom/pingfangx/study/tutorial/learning_the_java_language/classes_and_objects/init_fields/InitializerBlockTest;
        ALOAD 0
        INVOKESPECIAL java/lang/Object.<init> ()V
       L1
        LINENUMBER 13 L1
        ALOAD 0
        ICONST_1
        PUTFIELD com/pingfangx/study/tutorial/learning_the_java_language/classes_and_objects/init_fields/InitializerBlockTest$TestClass.field : I
       L2
        LINENUMBER 16 L2
        ALOAD 0
        ICONST_0
        PUTFIELD com/pingfangx/study/tutorial/learning_the_java_language/classes_and_objects/init_fields/InitializerBlockTest$TestClass.field : I
       L3
        LINENUMBER 19 L3
        ALOAD 0
        ICONST_2
        PUTFIELD com/pingfangx/study/tutorial/learning_the_java_language/classes_and_objects/init_fields/InitializerBlockTest$TestClass.field : I
       L4
        LINENUMBER 26 L4
        ALOAD 0
        //赋值为参数
        ILOAD 2
        PUTFIELD com/pingfangx/study/tutorial/learning_the_java_language/classes_and_objects/init_fields/InitializerBlockTest$TestClass.field : I
       L5
        LINENUMBER 27 L5
        RETURN
       L6
        LOCALVARIABLE this Lcom/pingfangx/study/tutorial/learning_the_java_language/classes_and_objects/init_fields/InitializerBlockTest$TestClass; L0 L6 0
        LOCALVARIABLE field I L0 L6 2
        MAXSTACK = 2
        MAXLOCALS = 3

      // access flags 0x1008
      static synthetic access$000(Lcom/pingfangx/study/tutorial/learning_the_java_language/classes_and_objects/init_fields/InitializerBlockTest$TestClass;)I
       L0
        LINENUMBER 11 L0
        ALOAD 0
        GETFIELD com/pingfangx/study/tutorial/learning_the_java_language/classes_and_objects/init_fields/InitializerBlockTest$TestClass.field : I
        IRETURN
       L1
        LOCALVARIABLE x0 Lcom/pingfangx/study/tutorial/learning_the_java_language/classes_and_objects/init_fields/InitializerBlockTest$TestClass; L0 L1 0
        MAXSTACK = 1
        MAXLOCALS = 1
    }
