R:
* 《JVMS》2.9
# 测试代码

    public class InitFieldTest {
        static int staticField1 = 1;
        static int staticField2 = 2;

        static {
            staticField1 = 1;
            int staticField3 = 3;
        }

        int field4 = 4;
        int field5 = 5;

        {
            field4 = 4;
            int field6 = 6;
        }

        public InitFieldTest(int field4) {
            this.field4 = field4;
        }

        public InitFieldTest(int field4, int field5) {
            this.field4 = field4;
            this.field5 = field5;
        }
    }

# 结论
* 初始化块或静态初始化块中声明的没有用字段会被优化删除（如 staticField3 和 field6）
* 静态字段初始化和静态初始化块会被组合到 static <clinit>()V
* 实例实段初始化和初始化块会被组合到每一个构造方法中，即各 public <init>()V 重载  
只会在声明的构造函数中，如果没有无参构造函数也不会添加
* 按行文顺序组合，即使重复赋值也是
# 字节码
    // class version 52.0 (52)
    // access flags 0x21
    public class com/pingfangx/study/tutorial/basic/java/javaoo/initfields/InitFieldTest {

      // compiled from: InitFieldTest.java

      // access flags 0x8
      static I staticField1

      // access flags 0x8
      static I staticField2

      // access flags 0x0
      I field4

      // access flags 0x0
      I field5

      // access flags 0x1
      public <init>(I)V
       L0
        LINENUMBER 24 L0
        ALOAD 0
        INVOKESPECIAL java/lang/Object.<init> ()V
       L1
        LINENUMBER 16 L1
        ALOAD 0
        ICONST_4
        PUTFIELD com/pingfangx/study/tutorial/basic/java/javaoo/initfields/InitFieldTest.field4 : I
       L2
        LINENUMBER 17 L2
        ALOAD 0
        ICONST_5
        PUTFIELD com/pingfangx/study/tutorial/basic/java/javaoo/initfields/InitFieldTest.field5 : I
       L3
        LINENUMBER 20 L3
        ALOAD 0
        ICONST_4
        PUTFIELD com/pingfangx/study/tutorial/basic/java/javaoo/initfields/InitFieldTest.field4 : I
       L4
        LINENUMBER 21 L4
        BIPUSH 6
        ISTORE 2
       L5
        LINENUMBER 25 L5
        ALOAD 0
        ILOAD 1
        PUTFIELD com/pingfangx/study/tutorial/basic/java/javaoo/initfields/InitFieldTest.field4 : I
       L6
        LINENUMBER 26 L6
        RETURN
       L7
        LOCALVARIABLE this Lcom/pingfangx/study/tutorial/basic/java/javaoo/initfields/InitFieldTest; L0 L7 0
        LOCALVARIABLE field4 I L0 L7 1
        MAXSTACK = 2
        MAXLOCALS = 3

      // access flags 0x1
      public <init>(II)V
       L0
        LINENUMBER 28 L0
        ALOAD 0
        INVOKESPECIAL java/lang/Object.<init> ()V
       L1
        LINENUMBER 16 L1
        ALOAD 0
        ICONST_4
        PUTFIELD com/pingfangx/study/tutorial/basic/java/javaoo/initfields/InitFieldTest.field4 : I
       L2
        LINENUMBER 17 L2
        ALOAD 0
        ICONST_5
        PUTFIELD com/pingfangx/study/tutorial/basic/java/javaoo/initfields/InitFieldTest.field5 : I
       L3
        LINENUMBER 20 L3
        ALOAD 0
        ICONST_4
        PUTFIELD com/pingfangx/study/tutorial/basic/java/javaoo/initfields/InitFieldTest.field4 : I
       L4
        LINENUMBER 21 L4
        BIPUSH 6
        ISTORE 3
       L5
        LINENUMBER 29 L5
        ALOAD 0
        ILOAD 1
        PUTFIELD com/pingfangx/study/tutorial/basic/java/javaoo/initfields/InitFieldTest.field4 : I
       L6
        LINENUMBER 30 L6
        ALOAD 0
        ILOAD 2
        PUTFIELD com/pingfangx/study/tutorial/basic/java/javaoo/initfields/InitFieldTest.field5 : I
       L7
        LINENUMBER 31 L7
        RETURN
       L8
        LOCALVARIABLE this Lcom/pingfangx/study/tutorial/basic/java/javaoo/initfields/InitFieldTest; L0 L8 0
        LOCALVARIABLE field4 I L0 L8 1
        LOCALVARIABLE field5 I L0 L8 2
        MAXSTACK = 2
        MAXLOCALS = 4

      // access flags 0x8
      static <clinit>()V
       L0
        LINENUMBER 8 L0
        ICONST_1
        PUTSTATIC com/pingfangx/study/tutorial/basic/java/javaoo/initfields/InitFieldTest.staticField1 : I
       L1
        LINENUMBER 9 L1
        ICONST_2
        PUTSTATIC com/pingfangx/study/tutorial/basic/java/javaoo/initfields/InitFieldTest.staticField2 : I
       L2
        LINENUMBER 12 L2
        ICONST_1
        PUTSTATIC com/pingfangx/study/tutorial/basic/java/javaoo/initfields/InitFieldTest.staticField1 : I
       L3
        LINENUMBER 13 L3
        ICONST_3
        ISTORE 0
       L4
        LINENUMBER 14 L4
        RETURN
        MAXSTACK = 1
        MAXLOCALS = 1
    }
# clinit 中的是什么意思
可能是 Class Loader 或者就是 Class吧。